MANIFEST.in
README.md
setup.cfg
setup.py
Data_viz.egg-info/PKG-INFO
Data_viz.egg-info/SOURCES.txt
Data_viz.egg-info/dependency_links.txt
Data_viz.egg-info/entry_points.txt
Data_viz.egg-info/requires.txt
Data_viz.egg-info/top_level.txt
bin/launch_viz
data_viz/__init__.py
data_viz/cluster_diving.py
data_viz/clustering.py
data_viz/config.new.py
data_viz/config.py
data_viz/dim_reduction.py
data_viz/labelling.py
data_viz/launch_viz.py
data_viz/ml_helpers.py
data_viz/qt_creator.py
data_viz/qt_handler.py
data_viz/utils.py
data_viz/vizualization.py
data_viz/requirements/requirements.txt