Metadata-Version: 1.0
Name: Data-viz
Version: 0.13
Summary: Represents your high-dimensional datas in a 2D space and play wih it
Home-page: UNKNOWN
Author: Sofian Medbouhi
Author-email: sof.m.sk@free.fr
License: GPL V3
Platform: UNKNOWN
